{
  "updated": "2026-07-06T07:00:48.788891",
  "data_date": "2026-07-06",
  "rankings": {
    "7d": [
      {
        "symbol": "SI=F",
        "name": "现货白银",
        "current": 62.81,
        "target": 64.35,
        "pct": 2.45,
        "low": 64.35,
        "high": 64.35
      },
      {
        "symbol": "ZM=F",
        "name": "豆粕",
        "current": 319.8,
        "target": 320.96,
        "pct": 0.36,
        "low": 320.96,
        "high": 320.96
      },
      {
        "symbol": "GC=F",
        "name": "现货黄金",
        "current": 4177.0,
        "target": 4179.44,
        "pct": 0.06,
        "low": 4179.44,
        "high": 4179.44
      },
      {
        "symbol": "HG=F",
        "name": "COMEX铜",
        "current": 630.15,
        "target": 630.56,
        "pct": 0.06,
        "low": 630.56,
        "high": 630.56
      },
      {
        "symbol": "AH=F",
        "name": "LME铝",
        "current": 3107.0,
        "target": 3103.36,
        "pct": -0.12,
        "low": 3103.36,
        "high": 3103.36
      },
      {
        "symbol": "CL=F",
        "name": "国际原油",
        "current": 68.49,
        "target": 67.89,
        "pct": -0.88,
        "low": 67.89,
        "high": 67.89
      }
    ],
    "14d": [
      {
        "symbol": "SI=F",
        "name": "现货白银",
        "current": 62.81,
        "target": 64.21,
        "pct": 2.22,
        "low": 64.21,
        "high": 64.21
      },
      {
        "symbol": "ZM=F",
        "name": "豆粕",
        "current": 319.8,
        "target": 321.42,
        "pct": 0.51,
        "low": 321.42,
        "high": 321.42
      },
      {
        "symbol": "AH=F",
        "name": "LME铝",
        "current": 3107.0,
        "target": 3103.99,
        "pct": -0.1,
        "low": 3103.99,
        "high": 3103.99
      },
      {
        "symbol": "HG=F",
        "name": "COMEX铜",
        "current": 630.15,
        "target": 629.31,
        "pct": -0.13,
        "low": 629.31,
        "high": 629.31
      },
      {
        "symbol": "GC=F",
        "name": "现货黄金",
        "current": 4177.0,
        "target": 4170.14,
        "pct": -0.16,
        "low": 4170.14,
        "high": 4170.14
      },
      {
        "symbol": "CL=F",
        "name": "国际原油",
        "current": 68.49,
        "target": 67.42,
        "pct": -1.56,
        "low": 67.42,
        "high": 67.42
      }
    ],
    "30d": [
      {
        "symbol": "SI=F",
        "name": "现货白银",
        "current": 62.81,
        "target": 63.79,
        "pct": 1.56,
        "low": 63.79,
        "high": 63.79
      },
      {
        "symbol": "ZM=F",
        "name": "豆粕",
        "current": 319.8,
        "target": 321.39,
        "pct": 0.5,
        "low": 321.39,
        "high": 321.39
      },
      {
        "symbol": "AH=F",
        "name": "LME铝",
        "current": 3107.0,
        "target": 3110.9,
        "pct": 0.13,
        "low": 3110.9,
        "high": 3110.9
      },
      {
        "symbol": "GC=F",
        "name": "现货黄金",
        "current": 4177.0,
        "target": 4157.16,
        "pct": -0.48,
        "low": 4157.16,
        "high": 4157.16
      },
      {
        "symbol": "HG=F",
        "name": "COMEX铜",
        "current": 630.15,
        "target": 626.35,
        "pct": -0.6,
        "low": 626.35,
        "high": 626.35
      },
      {
        "symbol": "CL=F",
        "name": "国际原油",
        "current": 68.49,
        "target": 66.58,
        "pct": -2.78,
        "low": 66.58,
        "high": 66.58
      }
    ],
    "60d": [
      {
        "symbol": "AH=F",
        "name": "LME铝",
        "current": 3107.0,
        "target": 3137.43,
        "pct": 0.98,
        "low": 3137.43,
        "high": 3137.43
      },
      {
        "symbol": "ZM=F",
        "name": "豆粕",
        "current": 319.8,
        "target": 321.3,
        "pct": 0.47,
        "low": 321.3,
        "high": 321.3
      },
      {
        "symbol": "SI=F",
        "name": "现货白银",
        "current": 62.81,
        "target": 62.88,
        "pct": 0.11,
        "low": 62.88,
        "high": 62.88
      },
      {
        "symbol": "GC=F",
        "name": "现货黄金",
        "current": 4177.0,
        "target": 4156.5,
        "pct": -0.49,
        "low": 4156.5,
        "high": 4156.5
      },
      {
        "symbol": "HG=F",
        "name": "COMEX铜",
        "current": 630.15,
        "target": 618.11,
        "pct": -1.91,
        "low": 618.11,
        "high": 618.11
      },
      {
        "symbol": "CL=F",
        "name": "国际原油",
        "current": 68.49,
        "target": 66.27,
        "pct": -3.25,
        "low": 66.27,
        "high": 66.27
      }
    ],
    "90d": [
      {
        "symbol": "AH=F",
        "name": "LME铝",
        "current": 3107.0,
        "target": 3131.66,
        "pct": 0.79,
        "low": 3131.66,
        "high": 3131.66
      },
      {
        "symbol": "ZM=F",
        "name": "豆粕",
        "current": 319.8,
        "target": 321.2,
        "pct": 0.44,
        "low": 321.2,
        "high": 321.2
      },
      {
        "symbol": "GC=F",
        "name": "现货黄金",
        "current": 4177.0,
        "target": 4162.86,
        "pct": -0.34,
        "low": 4162.86,
        "high": 4162.86
      },
      {
        "symbol": "SI=F",
        "name": "现货白银",
        "current": 62.81,
        "target": 61.1,
        "pct": -2.73,
        "low": 61.1,
        "high": 61.1
      },
      {
        "symbol": "HG=F",
        "name": "COMEX铜",
        "current": 630.15,
        "target": 611.8,
        "pct": -2.91,
        "low": 611.8,
        "high": 611.8
      },
      {
        "symbol": "CL=F",
        "name": "国际原油",
        "current": 68.49,
        "target": 66.12,
        "pct": -3.46,
        "low": 66.12,
        "high": 66.12
      }
    ]
  },
  "details": [
    {
      "symbol": "GC=F",
      "name": "现货黄金",
      "current": 4177.0,
      "pred_7d": {
        "target": 4179.44,
        "pct": 0.06,
        "low": 4179.44,
        "high": 4179.44
      },
      "pred_14d": {
        "target": 4170.14,
        "pct": -0.16,
        "low": 4170.14,
        "high": 4170.14
      },
      "pred_30d": {
        "target": 4157.16,
        "pct": -0.48,
        "low": 4157.16,
        "high": 4157.16
      },
      "pred_60d": {
        "target": 4156.5,
        "pct": -0.49,
        "low": 4156.5,
        "high": 4156.5
      },
      "pred_90d": {
        "target": 4162.86,
        "pct": -0.34,
        "low": 4162.86,
        "high": 4162.86
      }
    },
    {
      "symbol": "SI=F",
      "name": "现货白银",
      "current": 62.81,
      "pred_7d": {
        "target": 64.35,
        "pct": 2.45,
        "low": 64.35,
        "high": 64.35
      },
      "pred_14d": {
        "target": 64.21,
        "pct": 2.22,
        "low": 64.21,
        "high": 64.21
      },
      "pred_30d": {
        "target": 63.79,
        "pct": 1.56,
        "low": 63.79,
        "high": 63.79
      },
      "pred_60d": {
        "target": 62.88,
        "pct": 0.11,
        "low": 62.88,
        "high": 62.88
      },
      "pred_90d": {
        "target": 61.1,
        "pct": -2.73,
        "low": 61.1,
        "high": 61.1
      }
    },
    {
      "symbol": "CL=F",
      "name": "国际原油",
      "current": 68.49,
      "pred_7d": {
        "target": 67.89,
        "pct": -0.88,
        "low": 67.89,
        "high": 67.89
      },
      "pred_14d": {
        "target": 67.42,
        "pct": -1.56,
        "low": 67.42,
        "high": 67.42
      },
      "pred_30d": {
        "target": 66.58,
        "pct": -2.78,
        "low": 66.58,
        "high": 66.58
      },
      "pred_60d": {
        "target": 66.27,
        "pct": -3.25,
        "low": 66.27,
        "high": 66.27
      },
      "pred_90d": {
        "target": 66.12,
        "pct": -3.46,
        "low": 66.12,
        "high": 66.12
      }
    },
    {
      "symbol": "HG=F",
      "name": "COMEX铜",
      "current": 630.15,
      "pred_7d": {
        "target": 630.56,
        "pct": 0.06,
        "low": 630.56,
        "high": 630.56
      },
      "pred_14d": {
        "target": 629.31,
        "pct": -0.13,
        "low": 629.31,
        "high": 629.31
      },
      "pred_30d": {
        "target": 626.35,
        "pct": -0.6,
        "low": 626.35,
        "high": 626.35
      },
      "pred_60d": {
        "target": 618.11,
        "pct": -1.91,
        "low": 618.11,
        "high": 618.11
      },
      "pred_90d": {
        "target": 611.8,
        "pct": -2.91,
        "low": 611.8,
        "high": 611.8
      }
    },
    {
      "symbol": "AH=F",
      "name": "LME铝",
      "current": 3107.0,
      "pred_7d": {
        "target": 3103.36,
        "pct": -0.12,
        "low": 3103.36,
        "high": 3103.36
      },
      "pred_14d": {
        "target": 3103.99,
        "pct": -0.1,
        "low": 3103.99,
        "high": 3103.99
      },
      "pred_30d": {
        "target": 3110.9,
        "pct": 0.13,
        "low": 3110.9,
        "high": 3110.9
      },
      "pred_60d": {
        "target": 3137.43,
        "pct": 0.98,
        "low": 3137.43,
        "high": 3137.43
      },
      "pred_90d": {
        "target": 3131.66,
        "pct": 0.79,
        "low": 3131.66,
        "high": 3131.66
      }
    },
    {
      "symbol": "ZM=F",
      "name": "豆粕",
      "current": 319.8,
      "pred_7d": {
        "target": 320.96,
        "pct": 0.36,
        "low": 320.96,
        "high": 320.96
      },
      "pred_14d": {
        "target": 321.42,
        "pct": 0.51,
        "low": 321.42,
        "high": 321.42
      },
      "pred_30d": {
        "target": 321.39,
        "pct": 0.5,
        "low": 321.39,
        "high": 321.39
      },
      "pred_60d": {
        "target": 321.3,
        "pct": 0.47,
        "low": 321.3,
        "high": 321.3
      },
      "pred_90d": {
        "target": 321.2,
        "pct": 0.44,
        "low": 321.2,
        "high": 321.2
      }
    }
  ]
}